datero/__init__.py
datero/admin.py
datero/app.py
datero/config.py
datero/connection.py
datero/main.py
datero/adapter/__init__.py
datero/adapter/adapter.py
datero/adapter/mysql.py
datero/adapter/oracle.py
datero/adapter/postgres.py
datero/config/config.yaml
datero/config/default.yaml
datero/config/schema.yaml
datero/fdw/__init__.py
datero/fdw/extension.py
datero/fdw/schema.py
datero/fdw/server.py
datero/fdw/user.py
datero/fdw/util.py
datero-0.0.1.dist-info/LICENSE
datero-0.0.1.dist-info/METADATA
datero-0.0.1.dist-info/WHEEL
datero-0.0.1.dist-info/entry_points.txt
datero-0.0.1.dist-info/top_level.txt
datero-0.0.1.dist-info/RECORD
