Metadata-Version: 2.1
Name: datero
Version: 0.0.1
Summary: Datero Python Client
Author-email: Chumaky IT <info@chumaky.team>
License: MIT License
Project-URL: GitHub, https://github.com/chumaky/datero-python-client
Project-URL: Datero, https://datero.tech
Keywords: postgres,fdw,hsql
Classifier: Programming Language :: Python :: 3
Classifier: License :: OSI Approved :: MIT License
Classifier: Operating System :: OS Independent
Requires-Python: >=3.7
License-File: LICENSE
Requires-Dist: psycopg2
Requires-Dist: ruamel.yaml
